rvd_ap/__init__.py
rvd_ap/rvd_ap.py
rvd_ap-0.1.0.dist-info/LICENCE.txt
rvd_ap-0.1.0.dist-info/METADATA
rvd_ap-0.1.0.dist-info/WHEEL
rvd_ap-0.1.0.dist-info/top_level.txt
rvd_ap-0.1.0.dist-info/RECORD
