Metadata-Version: 2.1
Name: rvd_ap
Version: 0.1.0
Summary: My description will help you to pass time and understand my ability of writing codes
Home-page: https://github.com/AravindSreeU/rvd_ap
Author: ARAVIND SREE U
Author-email: uaravindsree@gmail.com
Classifier: Programming Language :: Python :: 3
Classifier: License :: OSI Approved :: MIT License
Classifier: Operating System :: OS Independent
Requires-Python: >=3.6
License-File: LICENCE.txt
